Metadata-Version: 2.4
Name: mcp-server-pacman
Version: 0.2.0
Summary: A Model Context Protocol server providing tools to query package indices like PyPI, npm, and crates.io
Author: Oliver Borchers
License: MIT
License-File: LICENSE
Keywords: automation,crates,llm,mcp,npm,pypi
Classifier: Development Status :: 4 - Beta
Classifier: Intended Audience :: Developers
Classifier: License :: OSI Approved :: MIT License
Classifier: Programming Language :: Python :: 3
Classifier: Programming Language :: Python :: 3.11
Requires-Python: >=3.11
Requires-Dist: cachetools>=5.3.0
Requires-Dist: httpx<0.28
Requires-Dist: loguru>=0.7.3
Requires-Dist: mcp>=1.1.3
Requires-Dist: pydantic>=2.0.0
